genpyi/__init__.py
genpyi/__main__.py
genpyi/_compat.py
genpyi/_typing.py
genpyi/cli.py
genpyi/converter.py
genpyi/generator.py
genpyi/py.typed
genpyi/stub_element.py
genpyi-0.2.0.data/scripts/genpyi
genpyi-0.2.0.dist-info/LICENSE
genpyi-0.2.0.dist-info/METADATA
genpyi-0.2.0.dist-info/WHEEL
genpyi-0.2.0.dist-info/top_level.txt
genpyi-0.2.0.dist-info/RECORD
