Metadata-Version: 2.1
Name: genpyi
Version: 0.2.0
Summary: A Python stub generator from genmsg specs
Home-page: https://github.com/rospypi/genpyi/
Author: Yuki Igarashi, Tamamki Nishino
Author-email: me@bonprosoft.com, otamachan@gmail.com
License: Apache License 2.0
Platform: UNKNOWN
Classifier: License :: OSI Approved :: Apache Software License
Classifier: Operating System :: MacOS
Classifier: Operating System :: Microsoft :: Windows
Classifier: Operating System :: POSIX
Classifier: Operating System :: Unix
Classifier: Programming Language :: Python :: 2.7
Classifier: Programming Language :: Python :: 3.6
Classifier: Programming Language :: Python :: 3.7
Classifier: Programming Language :: Python :: 3.8
Classifier: Programming Language :: Python :: 3.9
Classifier: Programming Language :: Python
Requires-Dist: genmsg
Requires-Dist: genpy
Provides-Extra: dev
Requires-Dist: pytest (<5.0,>=4.6) ; extra == 'dev'
Requires-Dist: typing ; (python_version == "2.7") and extra == 'dev'
Provides-Extra: lint
Requires-Dist: black (==20.8b1) ; extra == 'lint'
Requires-Dist: flake8-bugbear (==21.4.3) ; extra == 'lint'
Requires-Dist: flake8 (==3.9.1) ; extra == 'lint'
Requires-Dist: isort (==5.1.4) ; extra == 'lint'
Requires-Dist: mypy (==0.790) ; extra == 'lint'
Requires-Dist: pysen (<0.10,>=0.9) ; extra == 'lint'
